{
	"info": {
		"_postman_id": "ff78fed0-2342-4c57-807f-a9b555345476",
		"name": "API-GestionLibros",
		"schema": "https://schema.getpostman.com/json/collection/v2.1.0/collection.json",
		"_exporter_id": "26996892"
	},
	"item": [
		{
			"name": "BooksAll",
			"request": {
				"method": "GET",
				"header": [],
				"url": {
					"raw": "http://localhost/api/public/books/get",
					"protocol": "http",
					"host": [
						"localhost"
					],
					"path": [
						"api",
						"public",
						"books",
						"get"
					]
				}
			},
			"response": []
		},
		{
			"name": "BooksId",
			"request": {
				"method": "GET",
				"header": [],
				"url": {
					"raw": "http://localhost/api/public/books/get/4",
					"protocol": "http",
					"host": [
						"localhost"
					],
					"path": [
						"api",
						"public",
						"books",
						"get",
						"4"
					]
				}
			},
			"response": []
		},
		{
			"name": "BookCreate",
			"request": {
				"method": "POST",
				"header": [],
				"body": {
					"mode": "raw",
					"raw": "{\r\n    \"title\": \"Libro Nuevo 12\",\r\n    \"author\": \"Juan Lpez\",\r\n    \"category\": \"Ficcion\",\r\n    \"price\": 20,\r\n    \"stock\": 5\r\n}",
					"options": {
						"raw": {
							"language": "json"
						}
					}
				},
				"url": {
					"raw": "http://localhost/api/public/books/create",
					"protocol": "http",
					"host": [
						"localhost"
					],
					"path": [
						"api",
						"public",
						"books",
						"create"
					]
				}
			},
			"response": []
		},
		{
			"name": "BookUpdate",
			"request": {
				"method": "PUT",
				"header": [],
				"body": {
					"mode": "raw",
					"raw": "{\r\n    \"price\": 20,\r\n    \"stock\": 7\r\n}",
					"options": {
						"raw": {
							"language": "json"
						}
					}
				},
				"url": {
					"raw": "http://localhost/api/public/books/update/11",
					"protocol": "http",
					"host": [
						"localhost"
					],
					"path": [
						"api",
						"public",
						"books",
						"update",
						"11"
					]
				}
			},
			"response": []
		},
		{
			"name": "BookDelete",
			"request": {
				"method": "DELETE",
				"header": [],
				"url": {
					"raw": "http://localhost/api/public/books/delete/12",
					"protocol": "http",
					"host": [
						"localhost"
					],
					"path": [
						"api",
						"public",
						"books",
						"delete",
						"12"
					]
				}
			},
			"response": []
		}
	]
}